{
    "type": "comments",
    "list": [
    {
        "id" : "1",
        "author": "Иван",
        "product_id": "1",
        "text": "Очень хороший товар",
        "date": "1 сентября 2020"
    },
    {
        "id" : "2",
        "author": "Алекс",
        "product_id": "2",
        "text": "Очень хороший товар",
        "date": "1 сентября 2020"
    },
    {
        "id" : "3",
        "author": "Саша",
        "product_id": "2",
        "text": "Очень хороший товар",
        "date": "1 сентября 2020"
    },
    {
        "id" : "4",
        "author": "Егор",
        "product_id": "2",
        "text": "Очень хороший товар",
        "date": "1 сентября 2020"
    },
    {
        "id" : "5",
        "author": "Иван",
        "product_id": "3",
        "text": "Очень хороший товар",
        "date": "1 сентября 2020"
    },
    {
        "id" : "6",
        "author": "Дима",
        "product_id": "2",
        "text": "Очень хороший товар",
        "date": "1 сентября 2020"
    }
]
}
